topsis_experimental/__init__.py
topsis_experimental/__main__.py
topsis_experimental/topsis_experimental.py
topsis_experimental-0.9.dist-info/METADATA
topsis_experimental-0.9.dist-info/WHEEL
topsis_experimental-0.9.dist-info/entry_points.txt
topsis_experimental-0.9.dist-info/top_level.txt
topsis_experimental-0.9.dist-info/RECORD
