Metadata-Version: 2.1
Name: topsis-experimental
Version: 0.9
Requires-Dist: pandas
Requires-Dist: numpy
Requires-Dist: scikit-learn
